midgy/__init__.py
midgy/__main__.py
midgy/_version.py
midgy/front_matter.py
midgy/lexers.py
midgy/loader.py
midgy/python.py
midgy/render.py
midgy-2023.2.14.dist-info/METADATA
midgy-2023.2.14.dist-info/WHEEL
midgy-2023.2.14.dist-info/entry_points.txt
midgy-2023.2.14.dist-info/licenses/LICENSE
midgy-2023.2.14.dist-info/RECORD
