Metadata-Version: 2.1
Name: midgy
Version: 2023.2.14
Summary: run markdown as python code
Project-URL: Documentation, https://github.com/deathbeds/midgy#readme
Project-URL: Issues, https://github.com/deathbeds/midgy/issues
Project-URL: Source, https://github.com/deathbeds/midgy
Author-email: tonyfast <tony.fast@gmail.com>
License-File: LICENSE
Classifier: Development Status :: 4 - Beta
Classifier: License :: OSI Approved :: BSD License
Classifier: Natural Language :: English
Classifier: Programming Language :: Python
Classifier: Programming Language :: Python :: 3.7
Classifier: Programming Language :: Python :: 3.8
Classifier: Programming Language :: Python :: 3.9
Classifier: Programming Language :: Python :: 3.10
Classifier: Programming Language :: Python :: 3.11
Classifier: Programming Language :: Python :: Implementation :: CPython
Classifier: Programming Language :: Python :: Implementation :: PyPy
Requires-Python: >=3.7
Requires-Dist: importnb
Requires-Dist: markdown-it-py[linkify,plugins]
Provides-Extra: black
Requires-Dist: black; extra == 'black'
Provides-Extra: rich
Requires-Dist: rich; extra == 'rich'
Provides-Extra: test
Requires-Dist: pytest; extra == 'test'
